sandock/__init__.py
sandock/_version.py
sandock/cli.py
sandock/config/__init__.py
sandock/config/_helpers.py
sandock/config/backup.py
sandock/config/config.py
sandock/config/image.py
sandock/config/program.py
sandock/exceptions.py
sandock/executors/__init__.py
sandock/executors/apple_container.py
sandock/sandbox.py
sandock/shared.py
sandock/volume.py
sandock-0.7.1.dist-info/LICENSE
sandock-0.7.1.dist-info/METADATA
sandock-0.7.1.dist-info/WHEEL
sandock-0.7.1.dist-info/entry_points.txt
sandock-0.7.1.dist-info/RECORD
