Metadata-Version: 2.3
Name: sandock
Version: 0.7.1
Summary: CLI tool for sandbox execution using container approach
License: MIT
Author: Imam Omar Mochtar
Author-email: iomarmochtar@gmail.com
Requires-Python: >=3.9
Classifier: License :: OSI Approved :: MIT License
Classifier: Programming Language :: Python :: 3
Classifier: Programming Language :: Python :: 3.9
Classifier: Programming Language :: Python :: 3.10
Classifier: Programming Language :: Python :: 3.11
Classifier: Programming Language :: Python :: 3.12
Classifier: Programming Language :: Python :: 3.13
Provides-Extra: yml-config
Requires-Dist: pyyaml (>=6.0.2,<7.0.0) ; extra == "yml-config"
Project-URL: Repository, https://github.com/iomarmochtar/sandock
